<?xml version="1.0" encoding="UTF-8" standalone="yes"?>
<trpDocMetadata>
    <docId>434476</docId>
    <title>ArthurSchnitzler_Briefe_1875_1912_Inhalt</title>
    <uploadTimestamp>1594876181828</uploadTimestamp>
    <uploader>walter.obweger@gmail.com</uploader>
    <uploaderId>65134</uploaderId>
    <nrOfPages>6</nrOfPages>
    <pageId>17615509</pageId>
    <url>https://files.transkribus.eu/Get?id=SANYCZSSKUDLJSWXTDZMUUVC&amp;fileType=view</url>
    <thumbUrl>https://files.transkribus.eu/Get?id=SANYCZSSKUDLJSWXTDZMUUVC&amp;fileType=thumb</thumbUrl>
    <status>0</status>
    <fimgStoreColl>TrpDoc_DEA_434476</fimgStoreColl>
    <origDocId>0</origDocId>
    <collectionList>
        <colList>
            <colId>71755</colId>
            <colName>walter.obweger@gmail.com Collection</colName>
            <description>walter.obweger@gmail.com</description>
            <crowdsourcing>false</crowdsourcing>
            <elearning>false</elearning>
            <nrOfDocuments>0</nrOfDocuments>
        </colList>
    </collectionList>
</trpDocMetadata>
